dailyutils/__init__.py
dailyutils/daily_notifier.py
dailyutils/date_utils.py
dailyutils/expense_logger.py
dailyutils/password_utils.py
dailyutils/unit_converter.py
dailyutils_aniket-0.1.1.dist-info/licenses/LICENSE
dailyutils_aniket-0.1.1.dist-info/METADATA
dailyutils_aniket-0.1.1.dist-info/WHEEL
dailyutils_aniket-0.1.1.dist-info/top_level.txt
dailyutils_aniket-0.1.1.dist-info/RECORD
